med/__init__.py
med/admin.py
med/apps.py
med/forms.py
med/google_api.py
med/models.py
med/tests.py
med/util.py
med/utils.py
med/views.py
med/migrations/0001_initial.py
med/migrations/0002_used_alter_rdv_prixprop.py
med/migrations/0003_patient_isop.py
med/migrations/0004_remove_rdv_nature_remove_rdv_prixprop_patient_nature_and_more.py
med/migrations/0005_rec_remove_assistant_role_user_is_receptionist_and_more.py
med/migrations/0006_assistant_doctor_assistant_dr.py
med/migrations/0007_remove_assistant_doctor_remove_assistant_dr_and_more.py
med/migrations/0008_patient_prix.py
med/migrations/0009_remove_user_age.py
med/migrations/0010_user_age.py
med/migrations/0011_dctr_prc_dctr_prccherg.py
med/migrations/0012_patient_orient.py
med/migrations/0013_food_dt_medecines_dt_used_dt.py
med/migrations/0014_alter_patient_currentstate.py
med/migrations/0015_alter_patient_currentstate.py
med/migrations/0016_patient_bed_alter_user_is_admin.py
med/migrations/0017_alter_patient_bed_alter_patient_orient_and_more.py
med/migrations/__init__.py
med-0.0.1.data/scripts/manage.py
medapp/__init__.py
medapp/asgi.py
medapp/settings.py
medapp/urls.py
medapp/wsgi.py
med-0.0.1.dist-info/METADATA
med-0.0.1.dist-info/WHEEL
med-0.0.1.dist-info/top_level.txt
med-0.0.1.dist-info/RECORD
