Metadata-Version: 2.1
Name: med
Version: 0.0.1
Summary: Django project
Home-page: https://github.com/mag1i/med.git
Author: Maggie
Author-email: bechmanel@gmail.com
License: MIT
Project-URL: Bug Tracker, https://github.com/mag1i/med.git/issues
Platform: UNKNOWN
Classifier: Programming Language :: Python :: 3
Classifier: Operating System :: OS Independent
Requires-Python: >=3.9
Requires-Dist: Django (>=2.2)
